agentforce/__init__.py
agentforce/specs.py
agentforce/tool_executor.py
agentforce/tools.py
agentforce/utils.py
agentforce/llms/__init__.py
agentforce/llms/_cohere.py
agentforce/llms/_llamacpp.py
agentforce/llms/_openai.py
agentforce/llms/llm.py
agentforce-0.0.1.dev1.dist-info/licenses/LICENSE
agentforce-0.0.1.dev1.dist-info/METADATA
agentforce-0.0.1.dev1.dist-info/WHEEL
agentforce-0.0.1.dev1.dist-info/top_level.txt
agentforce-0.0.1.dev1.dist-info/RECORD
