Metadata-Version: 2.4
Name: agentforce
Version: 0.0.1.dev1
License-File: LICENSE
Requires-Dist: langchain
Requires-Dist: langchain-community>=0.0.36
Requires-Dist: langchainhub>=0.1.15
Requires-Dist: llama_cpp_python
Requires-Dist: pandas
Requires-Dist: loguru
Requires-Dist: wikipedia
Requires-Dist: googlesearch-python
Requires-Dist: langchain-cohere
Requires-Dist: transformers
Requires-Dist: openai
Requires-Dist: cohere
Requires-Dist: litserve
Dynamic: license-file
Dynamic: requires-dist
